optimisewait/__init__.py
optimisewait-0.6.1.dist-info/licenses/LICENSE
optimisewait-0.6.1.dist-info/METADATA
optimisewait-0.6.1.dist-info/WHEEL
optimisewait-0.6.1.dist-info/top_level.txt
optimisewait-0.6.1.dist-info/RECORD
