Metadata-Version: 2.4
Name: optimisewait
Version: 0.6.1
Summary: A Python utility for automated image detection and clicking
Home-page: https://github.com/AMAMazing/optimisewait
Author: Alex M
Classifier: Programming Language :: Python :: 3
Classifier: License :: OSI Approved :: MIT License
Classifier: Operating System :: OS Independent
Requires-Python: >=3.6
License-File: LICENSE
Requires-Dist: pyautogui>=0.9.53
Dynamic: author
Dynamic: classifier
Dynamic: description
Dynamic: description-content-type
Dynamic: home-page
Dynamic: license-file
Dynamic: requires-dist
Dynamic: requires-python
Dynamic: summary
